{
    "exercises": [
        {
            "forces": [
                "Weight",
                "Push",
                "Normal",
                "Tension",
                "Friction"
            ],
            "title": "Block",
            "inst": "instr/block.html",
            "img": "instr/diagrams/block2.png",
            "gif": "instr/diagrams/capture1.gif",
            "fb": {
                "0": "Normal",
                "180": "Weight"
            },
            "netForce": null,
            "rot": 0
        },
        {
            "forces": [
                "Normal",
                "Weight",
                "A on B",
                "B on A",
                "Push"
            ],
            "title": "Two Blocks",
            "inst": "instr/2blocks1.html",
            "img": "instr/diagrams/AonB.png",
            "fb": {
                "0": "Normal",
                "90": "Push",
                "180": "Weight",
                "270": "B on A"
            },
            "netForce": "90",
            "rot": 0
        },
        {
            "forces": [
                "Normal",
                "Weight",
                "Friction",
                "Push",
                "Tension"
            ],
            "title": "Curling",
            "inst": "instr/curling.html",
            "img": "instr/diagrams/curlingRock2.png",
            "fb": {
                "0": "Normal",
                "270": "Friction",
                "180": "Weight"
            },
            "netForce": "270",
            "rot": 0
        },
        {
            "forces": [
                "Normal",
                "Weight",
                "Friction",
                "Push",
                "Air"
            ],
            "title": "Football in air",
            "inst": "instr/football.html",
            "img": "instr/diagrams/football.png",
            "fb": {
                "180": "Weight"
            },
            "netForce": "180",
            "rot": 0
        },
        {
            "forces": [
                "Weight",
                "Push",
                "Normal",
                "Tension",
                "Friction"
            ],
            "title": "Pulling a block",
            "inst": "instr/pullBlock.html",
            "img": "instr/diagrams/DragBox.png",
            "gif": "instr/diagrams/capture1.gif",
            "fb": {
                "0": "Normal",
                "180": "Weight",
                "60": "Tension",
                "270": "Friction"
            },
            "netForce": "90",
            "rot": 60
        },
        {
            "forces": [
                "Weight",
                "Push",
                "Normal",
                "Tension",
                "Friction"
            ],
            "title": "A hard push!",
            "inst": "instr/hardPush.html",
            "img": "instr/diagrams/friction1.png",
            "gif": "instr/diagrams/capture1.gif",
            "fb": {
                "0": "Friction",
                "180": "Weight",
                "90": "Push"
            },
            "netForce": "90",
            "rot": 0
        },
        {
            "forces": [
                "Weight",
                "Push",
                "Normal",
                "Tension",
                "Friction"
            ],
            "title": "Pulleys 1",
            "inst": "instr/pulleys1.html",
            "img": "instr/diagrams/pulley1.png",
            "gif": "instr/diagrams/capture1.gif",
            "fb": {
                "0": "Normal",
                "180": "Weight",
                "90": "Tension",
                "270": "Friction"
            },
            "netForce": "90",
            "rot": 0
        },
        {
            "forces": [
                "Weight",
                "Push",
                "Normal",
                "Tension",
                "Friction"
            ],
            "title": "Pulleys 2",
            "inst": "instr/pulleys2.html",
            "img": "instr/diagrams/pulley2.png",
            "gif": "instr/diagrams/capture1.gif",
            "fb": {
                "180": "Weight",
                "36": "Normal",
                "126": "Friction",
                "306": "Tension"
            },
            "netForce": "306",
            "rot": 36
        },
        {
            "forces": [
                "Weight",
                "B on A",
                "A on B",
                "C on B",
                "Normal"
            ],
            "title": "Pulleys 3 (A)",
            "inst": "instr/pulleys3.html",
            "img": "instr/diagrams/pulley3.png",
            "gif": "instr/diagrams/capture1.gif",
            "fb": {
                "40": "B on A",
                "180": "Weight",
                "310": "Normal"
            },
            "netForce": null,
            "rot": 40
        },
        {
            "forces": [
                "Weight",
                "B on A",
                "A on B",
                "C on B",
                "Normal"
            ],
            "title": "Pulleys 3 (B)",
            "inst": "instr/pulleys3B.html",
            "img": "instr/diagrams/pulley3.png",
            "gif": "instr/diagrams/capture1.gif",
            "fb": {
                "18": "Normal",
                "108": "C on B",
                "180": "Weight",
                "288": "A on B"
            },
            "netForce": null,
            "rot": 18
        }
    ]
}